{"deviceOrientation":"portrait","openDataContext":"odc/","networkTimeout":{"request":60000,"connectSocket":60000,"uploadFile":60000,"downloadFile":60000},"iOSHighPerformance":true,"resizable":false,"__warning__":"invalid game.json subpackages[3][\"meta\"]、game.json subpackages[4][\"meta\"]、game.json subpackages[5][\"meta\"]、game.json subpackages[6][\"meta\"]、game.json subpackages[7][\"meta\"]、game.json subpackages[8][\"meta\"]、game.json subpackages[9][\"meta\"]、game.json subpackages[10][\"meta\"]、game.json subpackages[11][\"meta\"]、game.json [\"iOSHighPerformance\"]","subPackages":[{"name":"game","root":"/subpackages/game/"},{"name":"miniGameScripts","root":"/subpackages/miniGameScripts/"},{"name":"TEST_REMOTE_MODULE","root":"/subpackages/TEST_REMOTE_MODULE/"},{"independent":true,"name":"playable-match3","root":"/playable-match3/wechatgame/","meta":{"type":"playable","playableOrientation":"portrait"}},{"independent":true,"name":"playable-oilRush","root":"/playable-oilRush/wechatgame/","meta":{"type":"playable","playableOrientation":"portrait"}},{"independent":true,"name":"playable-hanoiTower","root":"/playable-hanoiTower/wechatgame/","meta":{"type":"playable","playableOrientation":"portrait"}},{"independent":true,"name":"playable-kof","root":"/playable-kof/wechatgame/","meta":{"type":"playable","playableOrientation":"portrait"}},{"independent":true,"name":"playable-kof2","root":"/playable-kof2/wechatgame/","meta":{"type":"playable","playableOrientation":"portrait"}},{"independent":true,"name":"playable-cuiLian","root":"/playable-cuiLian/wechatgame/","meta":{"type":"playable","playableOrientation":"portrait"}},{"independent":true,"name":"playable-diaoyu","root":"/playable-diaoyu/wechatgame/","meta":{"type":"playable","playableOrientation":"portrait"}},{"independent":true,"name":"playable-chuangguan","root":"/playable-chuangguan/wechatgame/","meta":{"type":"playable","playableOrientation":"portrait"}},{"independent":true,"name":"playable-baojinbi","root":"/playable-baojinbi/wechatgame/","meta":{"type":"playable","playableOrientation":"portrait"}}],"subContext":"odc/"}